asyncmaxbot-1.4.3.dist-info/licenses/LICENSE
maxbot/__init__.py
maxbot/bot.py
maxbot/dispatcher.py
maxbot/filters.py
maxbot/max_types.py
maxbot/middleware.py
maxbot/router.py
asyncmaxbot-1.4.3.dist-info/METADATA
asyncmaxbot-1.4.3.dist-info/WHEEL
asyncmaxbot-1.4.3.dist-info/entry_points.txt
asyncmaxbot-1.4.3.dist-info/top_level.txt
asyncmaxbot-1.4.3.dist-info/RECORD
