Metadata-Version: 2.4
Name: asyncmaxbot
Version: 1.4.3
Summary: Асинхронная библиотека для создания ботов в MaxAPI
Author-email: SDK Infotech <info@sdkinfotech.com>
Maintainer-email: SDK Infotech <info@sdkinfotech.com>
License: MIT
Project-URL: Homepage, https://github.com/sdkinfotech/asyncmaxbot
Project-URL: Documentation, https://sdkinfotech.github.io/asyncmaxbot/
Project-URL: Repository, https://github.com/sdkinfotech/asyncmaxbot
Project-URL: Bug Tracker, https://github.com/sdkinfotech/asyncmaxbot/issues
Project-URL: Release Notes, https://github.com/sdkinfotech/asyncmaxbot/blob/main/CHANGELOG.md
Keywords: bot,api,async,maxapi,messaging
Classifier: Development Status :: 4 - Beta
Classifier: Intended Audience :: Developers
Classifier: License :: OSI Approved :: MIT License
Classifier: Operating System :: OS Independent
Classifier: Programming Language :: Python :: 3
Classifier: Programming Language :: Python :: 3.8
Classifier: Programming Language :: Python :: 3.9
Classifier: Programming Language :: Python :: 3.10
Classifier: Programming Language :: Python :: 3.11
Classifier: Programming Language :: Python :: 3.12
Classifier: Topic :: Software Development :: Libraries :: Python Modules
Classifier: Topic :: Communications :: Chat
Classifier: Topic :: Internet :: WWW/HTTP :: Dynamic Content
Requires-Python: >=3.8
License-File: LICENSE
Requires-Dist: aiohttp>=3.8.0
Requires-Dist: pydantic>=2.0.0
Requires-Dist: typing-extensions>=4.0.0
Provides-Extra: dev
Requires-Dist: pytest>=7.0.0; extra == "dev"
Requires-Dist: pytest-asyncio>=0.21.0; extra == "dev"
Requires-Dist: pytest-cov>=4.0.0; extra == "dev"
Requires-Dist: black>=22.0.0; extra == "dev"
Requires-Dist: isort>=5.0.0; extra == "dev"
Requires-Dist: flake8>=5.0.0; extra == "dev"
Requires-Dist: mypy>=1.0.0; extra == "dev"
Provides-Extra: docs
Requires-Dist: mkdocs>=1.4.0; extra == "docs"
Requires-Dist: mkdocs-material>=8.0.0; extra == "docs"
Requires-Dist: mkdocstrings[python]>=0.20.0; extra == "docs"
Dynamic: license-file
